arnie/__init__.py
arnie/bpps.py
arnie/free_energy.py
arnie/mfe.py
arnie/mfe_bootstrap.py
arnie/pfunc.py
arnie/pk_predictors.py
arnie/sample_structures.py
arnie/utils.py
arnie/viz.py
arnie/mea/__init__.py
arnie/mea/mea.py
arnie/mea/mea_utils.py
arnie/mea/threshknot.py
arnie-0.2.7.dist-info/licenses/LICENSE
arnie-0.2.7.dist-info/METADATA
arnie-0.2.7.dist-info/WHEEL
arnie-0.2.7.dist-info/top_level.txt
arnie-0.2.7.dist-info/RECORD
