Metadata-Version: 2.4
Name: arnie
Version: 0.2.7
Summary: A Python utility library to estimate, compare, and reweight RNA energetics across many secondary structure algorithms.
Author-email: Das Lab <thedaslab@stanford.edu>
Project-URL: Homepage, https://github.com/DasLab/arnie
Project-URL: Documentation, https://daslab.github.io/arnie
Project-URL: Bug Tracker, https://github.com/DasLab/arnie/issues
Keywords: RNA,RNA structure prediction,Bioinformatics
Classifier: Programming Language :: Python :: 3
Classifier: License :: OSI Approved :: MIT License
Classifier: Operating System :: OS Independent
Requires-Python: >=3.7
License-File: LICENSE
Requires-Dist: numpy>=1.15
Requires-Dist: scipy>=1.5.0
Requires-Dist: matplotlib>=3.0.0
Dynamic: license-file
